Metadata-Version: 2.1
Name: kiteauth
Version: 1.0.2
Summary: Kite authentication library
Home-page: UNKNOWN
Author: @vatadepalli
Author-email: info@integriert.com
License: MIT
Keywords: kite authentication
Platform: UNKNOWN
Classifier: Development Status :: 5 - Production/Stable
Classifier: Intended Audience :: Developers
Classifier: Operating System :: OS Independent
Classifier: License :: OSI Approved :: MIT License
Classifier: Programming Language :: Python :: 3
License-File: LICENCE.txt
